{
  "id": "dabd1dcb-0dbe-402d-aaa7-70ac2790ea8a",
  "prevId": "e4628586-a0a3-404f-ab0a-a5d6910c65dc",
  "version": "7",
  "dialect": "postgresql",
  "tables": {
    "public.courses": {
      "name": "courses",
      "schema": "",
      "columns": {
        "id": {
          "name": "id",
          "type": "serial",
          "primaryKey": true,
          "notNull": true
        },
        "practice_id": {
          "name": "practice_id",
          "type": "integer",
          "primaryKey": false,
          "notNull": true
        },
        "title": {
          "name": "title",
          "type": "text",
          "primaryKey": false,
          "notNull": true
        },
        "subtitle": {
          "name": "subtitle",
          "type": "text",
          "primaryKey": false,
          "notNull": false
        },
        "category": {
          "name": "category",
          "type": "text",
          "primaryKey": false,
          "notNull": true,
          "default": "'front-office'"
        },
        "level": {
          "name": "level",
          "type": "course_level",
          "typeSchema": "public",
          "primaryKey": false,
          "notNull": true,
          "default": "'Beginner'"
        },
        "status": {
          "name": "status",
          "type": "course_status",
          "typeSchema": "public",
          "primaryKey": false,
          "notNull": true,
          "default": "'draft'"
        },
        "thumbnail": {
          "name": "thumbnail",
          "type": "text",
          "primaryKey": false,
          "notNull": false,
          "default": "'📚'"
        },
        "color": {
          "name": "color",
          "type": "text",
          "primaryKey": false,
          "notNull": false,
          "default": "'#3A63C2'"
        },
        "assigned_roles": {
          "name": "assigned_roles",
          "type": "text",
          "primaryKey": false,
          "notNull": false,
          "default": "''"
        },
        "created_at": {
          "name": "created_at",
          "type": "timestamp",
          "primaryKey": false,
          "notNull": true,
          "default": "now()"
        },
        "updated_at": {
          "name": "updated_at",
          "type": "timestamp",
          "primaryKey": false,
          "notNull": true,
          "default": "now()"
        }
      },
      "indexes": {
        "courses_practice_idx": {
          "name": "courses_practice_idx",
          "columns": [
            {
              "expression": "practice_id",
              "isExpression": false,
              "asc": true,
              "nulls": "last"
            }
          ],
          "isUnique": false,
          "concurrently": false,
          "method": "btree",
          "with": {}
        }
      },
      "foreignKeys": {
        "courses_practice_id_practices_id_fk": {
          "name": "courses_practice_id_practices_id_fk",
          "tableFrom": "courses",
          "tableTo": "practices",
          "columnsFrom": [
            "practice_id"
          ],
          "columnsTo": [
            "id"
          ],
          "onDelete": "no action",
          "onUpdate": "no action"
        }
      },
      "compositePrimaryKeys": {},
      "uniqueConstraints": {},
      "policies": {},
      "checkConstraints": {},
      "isRLSEnabled": false
    },
    "public.knowledge_docs": {
      "name": "knowledge_docs",
      "schema": "",
      "columns": {
        "id": {
          "name": "id",
          "type": "serial",
          "primaryKey": true,
          "notNull": true
        },
        "practice_id": {
          "name": "practice_id",
          "type": "integer",
          "primaryKey": false,
          "notNull": true
        },
        "title": {
          "name": "title",
          "type": "text",
          "primaryKey": false,
          "notNull": true
        },
        "type": {
          "name": "type",
          "type": "doc_type",
          "typeSchema": "public",
          "primaryKey": false,
          "notNull": true,
          "default": "'txt'"
        },
        "size_label": {
          "name": "size_label",
          "type": "text",
          "primaryKey": false,
          "notNull": false
        },
        "status": {
          "name": "status",
          "type": "doc_status",
          "typeSchema": "public",
          "primaryKey": false,
          "notNull": true,
          "default": "'processing'"
        },
        "scope": {
          "name": "scope",
          "type": "content_scope",
          "typeSchema": "public",
          "primaryKey": false,
          "notNull": true,
          "default": "'local'"
        },
        "tags": {
          "name": "tags",
          "type": "text",
          "primaryKey": false,
          "notNull": false,
          "default": "''"
        },
        "raw_content": {
          "name": "raw_content",
          "type": "text",
          "primaryKey": false,
          "notNull": false
        },
        "uploaded_at": {
          "name": "uploaded_at",
          "type": "timestamp",
          "primaryKey": false,
          "notNull": true,
          "default": "now()"
        },
        "uploaded_by_user_id": {
          "name": "uploaded_by_user_id",
          "type": "integer",
          "primaryKey": false,
          "notNull": false
        }
      },
      "indexes": {
        "docs_practice_idx": {
          "name": "docs_practice_idx",
          "columns": [
            {
              "expression": "practice_id",
              "isExpression": false,
              "asc": true,
              "nulls": "last"
            }
          ],
          "isUnique": false,
          "concurrently": false,
          "method": "btree",
          "with": {}
        }
      },
      "foreignKeys": {
        "knowledge_docs_practice_id_practices_id_fk": {
          "name": "knowledge_docs_practice_id_practices_id_fk",
          "tableFrom": "knowledge_docs",
          "tableTo": "practices",
          "columnsFrom": [
            "practice_id"
          ],
          "columnsTo": [
            "id"
          ],
          "onDelete": "no action",
          "onUpdate": "no action"
        },
        "knowledge_docs_uploaded_by_user_id_users_id_fk": {
          "name": "knowledge_docs_uploaded_by_user_id_users_id_fk",
          "tableFrom": "knowledge_docs",
          "tableTo": "users",
          "columnsFrom": [
            "uploaded_by_user_id"
          ],
          "columnsTo": [
            "id"
          ],
          "onDelete": "no action",
          "onUpdate": "no action"
        }
      },
      "compositePrimaryKeys": {},
      "uniqueConstraints": {},
      "policies": {},
      "checkConstraints": {},
      "isRLSEnabled": false
    },
    "public.lessons": {
      "name": "lessons",
      "schema": "",
      "columns": {
        "id": {
          "name": "id",
          "type": "serial",
          "primaryKey": true,
          "notNull": true
        },
        "module_id": {
          "name": "module_id",
          "type": "integer",
          "primaryKey": false,
          "notNull": true
        },
        "title": {
          "name": "title",
          "type": "text",
          "primaryKey": false,
          "notNull": true
        },
        "type": {
          "name": "type",
          "type": "lesson_type",
          "typeSchema": "public",
          "primaryKey": false,
          "notNull": true,
          "default": "'reading'"
        },
        "duration": {
          "name": "duration",
          "type": "text",
          "primaryKey": false,
          "notNull": false,
          "default": "'10 min'"
        },
        "content": {
          "name": "content",
          "type": "text",
          "primaryKey": false,
          "notNull": false
        },
        "position": {
          "name": "position",
          "type": "integer",
          "primaryKey": false,
          "notNull": true,
          "default": 0
        },
        "is_locked": {
          "name": "is_locked",
          "type": "boolean",
          "primaryKey": false,
          "notNull": false,
          "default": false
        },
        "created_at": {
          "name": "created_at",
          "type": "timestamp",
          "primaryKey": false,
          "notNull": true,
          "default": "now()"
        }
      },
      "indexes": {
        "lessons_module_idx": {
          "name": "lessons_module_idx",
          "columns": [
            {
              "expression": "module_id",
              "isExpression": false,
              "asc": true,
              "nulls": "last"
            }
          ],
          "isUnique": false,
          "concurrently": false,
          "method": "btree",
          "with": {}
        }
      },
      "foreignKeys": {
        "lessons_module_id_modules_id_fk": {
          "name": "lessons_module_id_modules_id_fk",
          "tableFrom": "lessons",
          "tableTo": "modules",
          "columnsFrom": [
            "module_id"
          ],
          "columnsTo": [
            "id"
          ],
          "onDelete": "cascade",
          "onUpdate": "no action"
        }
      },
      "compositePrimaryKeys": {},
      "uniqueConstraints": {},
      "policies": {},
      "checkConstraints": {},
      "isRLSEnabled": false
    },
    "public.modules": {
      "name": "modules",
      "schema": "",
      "columns": {
        "id": {
          "name": "id",
          "type": "serial",
          "primaryKey": true,
          "notNull": true
        },
        "course_id": {
          "name": "course_id",
          "type": "integer",
          "primaryKey": false,
          "notNull": true
        },
        "title": {
          "name": "title",
          "type": "text",
          "primaryKey": false,
          "notNull": true
        },
        "description": {
          "name": "description",
          "type": "text",
          "primaryKey": false,
          "notNull": false
        },
        "position": {
          "name": "position",
          "type": "integer",
          "primaryKey": false,
          "notNull": true,
          "default": 0
        },
        "created_at": {
          "name": "created_at",
          "type": "timestamp",
          "primaryKey": false,
          "notNull": true,
          "default": "now()"
        }
      },
      "indexes": {
        "modules_course_idx": {
          "name": "modules_course_idx",
          "columns": [
            {
              "expression": "course_id",
              "isExpression": false,
              "asc": true,
              "nulls": "last"
            }
          ],
          "isUnique": false,
          "concurrently": false,
          "method": "btree",
          "with": {}
        }
      },
      "foreignKeys": {
        "modules_course_id_courses_id_fk": {
          "name": "modules_course_id_courses_id_fk",
          "tableFrom": "modules",
          "tableTo": "courses",
          "columnsFrom": [
            "course_id"
          ],
          "columnsTo": [
            "id"
          ],
          "onDelete": "cascade",
          "onUpdate": "no action"
        }
      },
      "compositePrimaryKeys": {},
      "uniqueConstraints": {},
      "policies": {},
      "checkConstraints": {},
      "isRLSEnabled": false
    },
    "public.practices": {
      "name": "practices",
      "schema": "",
      "columns": {
        "id": {
          "name": "id",
          "type": "serial",
          "primaryKey": true,
          "notNull": true
        },
        "name": {
          "name": "name",
          "type": "text",
          "primaryKey": false,
          "notNull": true
        },
        "slug": {
          "name": "slug",
          "type": "text",
          "primaryKey": false,
          "notNull": true
        },
        "created_at": {
          "name": "created_at",
          "type": "timestamp",
          "primaryKey": false,
          "notNull": true,
          "default": "now()"
        }
      },
      "indexes": {},
      "foreignKeys": {},
      "compositePrimaryKeys": {},
      "uniqueConstraints": {
        "practices_slug_unique": {
          "name": "practices_slug_unique",
          "nullsNotDistinct": false,
          "columns": [
            "slug"
          ]
        }
      },
      "policies": {},
      "checkConstraints": {},
      "isRLSEnabled": false
    },
    "public.questionnaire_responses": {
      "name": "questionnaire_responses",
      "schema": "",
      "columns": {
        "id": {
          "name": "id",
          "type": "serial",
          "primaryKey": true,
          "notNull": true
        },
        "questionnaire_id": {
          "name": "questionnaire_id",
          "type": "integer",
          "primaryKey": false,
          "notNull": true
        },
        "user_id": {
          "name": "user_id",
          "type": "integer",
          "primaryKey": false,
          "notNull": true
        },
        "answers": {
          "name": "answers",
          "type": "text",
          "primaryKey": false,
          "notNull": true
        },
        "score": {
          "name": "score",
          "type": "integer",
          "primaryKey": false,
          "notNull": true
        },
        "passed": {
          "name": "passed",
          "type": "boolean",
          "primaryKey": false,
          "notNull": false,
          "default": false
        },
        "submitted_at": {
          "name": "submitted_at",
          "type": "timestamp",
          "primaryKey": false,
          "notNull": true,
          "default": "now()"
        }
      },
      "indexes": {
        "responses_questionnaire_idx": {
          "name": "responses_questionnaire_idx",
          "columns": [
            {
              "expression": "questionnaire_id",
              "isExpression": false,
              "asc": true,
              "nulls": "last"
            }
          ],
          "isUnique": false,
          "concurrently": false,
          "method": "btree",
          "with": {}
        },
        "responses_user_idx": {
          "name": "responses_user_idx",
          "columns": [
            {
              "expression": "user_id",
              "isExpression": false,
              "asc": true,
              "nulls": "last"
            }
          ],
          "isUnique": false,
          "concurrently": false,
          "method": "btree",
          "with": {}
        }
      },
      "foreignKeys": {
        "questionnaire_responses_questionnaire_id_questionnaires_id_fk": {
          "name": "questionnaire_responses_questionnaire_id_questionnaires_id_fk",
          "tableFrom": "questionnaire_responses",
          "tableTo": "questionnaires",
          "columnsFrom": [
            "questionnaire_id"
          ],
          "columnsTo": [
            "id"
          ],
          "onDelete": "cascade",
          "onUpdate": "no action"
        },
        "questionnaire_responses_user_id_users_id_fk": {
          "name": "questionnaire_responses_user_id_users_id_fk",
          "tableFrom": "questionnaire_responses",
          "tableTo": "users",
          "columnsFrom": [
            "user_id"
          ],
          "columnsTo": [
            "id"
          ],
          "onDelete": "cascade",
          "onUpdate": "no action"
        }
      },
      "compositePrimaryKeys": {},
      "uniqueConstraints": {},
      "policies": {},
      "checkConstraints": {},
      "isRLSEnabled": false
    },
    "public.questionnaires": {
      "name": "questionnaires",
      "schema": "",
      "columns": {
        "id": {
          "name": "id",
          "type": "serial",
          "primaryKey": true,
          "notNull": true
        },
        "course_id": {
          "name": "course_id",
          "type": "integer",
          "primaryKey": false,
          "notNull": true
        },
        "title": {
          "name": "title",
          "type": "text",
          "primaryKey": false,
          "notNull": true
        },
        "description": {
          "name": "description",
          "type": "text",
          "primaryKey": false,
          "notNull": false,
          "default": "''"
        },
        "passing_score": {
          "name": "passing_score",
          "type": "integer",
          "primaryKey": false,
          "notNull": false,
          "default": 70
        },
        "created_at": {
          "name": "created_at",
          "type": "timestamp",
          "primaryKey": false,
          "notNull": true,
          "default": "now()"
        },
        "updated_at": {
          "name": "updated_at",
          "type": "timestamp",
          "primaryKey": false,
          "notNull": true,
          "default": "now()"
        }
      },
      "indexes": {
        "questionnaires_course_idx": {
          "name": "questionnaires_course_idx",
          "columns": [
            {
              "expression": "course_id",
              "isExpression": false,
              "asc": true,
              "nulls": "last"
            }
          ],
          "isUnique": false,
          "concurrently": false,
          "method": "btree",
          "with": {}
        }
      },
      "foreignKeys": {
        "questionnaires_course_id_courses_id_fk": {
          "name": "questionnaires_course_id_courses_id_fk",
          "tableFrom": "questionnaires",
          "tableTo": "courses",
          "columnsFrom": [
            "course_id"
          ],
          "columnsTo": [
            "id"
          ],
          "onDelete": "cascade",
          "onUpdate": "no action"
        }
      },
      "compositePrimaryKeys": {},
      "uniqueConstraints": {},
      "policies": {},
      "checkConstraints": {},
      "isRLSEnabled": false
    },
    "public.questions": {
      "name": "questions",
      "schema": "",
      "columns": {
        "id": {
          "name": "id",
          "type": "serial",
          "primaryKey": true,
          "notNull": true
        },
        "questionnaire_id": {
          "name": "questionnaire_id",
          "type": "integer",
          "primaryKey": false,
          "notNull": true
        },
        "text": {
          "name": "text",
          "type": "text",
          "primaryKey": false,
          "notNull": true
        },
        "option_a": {
          "name": "option_a",
          "type": "text",
          "primaryKey": false,
          "notNull": true
        },
        "option_b": {
          "name": "option_b",
          "type": "text",
          "primaryKey": false,
          "notNull": true
        },
        "option_c": {
          "name": "option_c",
          "type": "text",
          "primaryKey": false,
          "notNull": true
        },
        "option_d": {
          "name": "option_d",
          "type": "text",
          "primaryKey": false,
          "notNull": true
        },
        "correct_option": {
          "name": "correct_option",
          "type": "text",
          "primaryKey": false,
          "notNull": true
        },
        "explanation": {
          "name": "explanation",
          "type": "text",
          "primaryKey": false,
          "notNull": false,
          "default": "''"
        },
        "position": {
          "name": "position",
          "type": "integer",
          "primaryKey": false,
          "notNull": true,
          "default": 0
        }
      },
      "indexes": {
        "questions_questionnaire_idx": {
          "name": "questions_questionnaire_idx",
          "columns": [
            {
              "expression": "questionnaire_id",
              "isExpression": false,
              "asc": true,
              "nulls": "last"
            }
          ],
          "isUnique": false,
          "concurrently": false,
          "method": "btree",
          "with": {}
        }
      },
      "foreignKeys": {
        "questions_questionnaire_id_questionnaires_id_fk": {
          "name": "questions_questionnaire_id_questionnaires_id_fk",
          "tableFrom": "questions",
          "tableTo": "questionnaires",
          "columnsFrom": [
            "questionnaire_id"
          ],
          "columnsTo": [
            "id"
          ],
          "onDelete": "cascade",
          "onUpdate": "no action"
        }
      },
      "compositePrimaryKeys": {},
      "uniqueConstraints": {},
      "policies": {},
      "checkConstraints": {},
      "isRLSEnabled": false
    },
    "public.roles": {
      "name": "roles",
      "schema": "",
      "columns": {
        "id": {
          "name": "id",
          "type": "serial",
          "primaryKey": true,
          "notNull": true
        },
        "practice_id": {
          "name": "practice_id",
          "type": "integer",
          "primaryKey": false,
          "notNull": true
        },
        "name": {
          "name": "name",
          "type": "text",
          "primaryKey": false,
          "notNull": true
        },
        "value": {
          "name": "value",
          "type": "text",
          "primaryKey": false,
          "notNull": true
        },
        "color": {
          "name": "color",
          "type": "text",
          "primaryKey": false,
          "notNull": false,
          "default": "'#3A63C2'"
        },
        "created_at": {
          "name": "created_at",
          "type": "timestamp",
          "primaryKey": false,
          "notNull": true,
          "default": "now()"
        }
      },
      "indexes": {
        "roles_value_practice_idx": {
          "name": "roles_value_practice_idx",
          "columns": [
            {
              "expression": "value",
              "isExpression": false,
              "asc": true,
              "nulls": "last"
            },
            {
              "expression": "practice_id",
              "isExpression": false,
              "asc": true,
              "nulls": "last"
            }
          ],
          "isUnique": true,
          "concurrently": false,
          "method": "btree",
          "with": {}
        },
        "roles_practice_idx": {
          "name": "roles_practice_idx",
          "columns": [
            {
              "expression": "practice_id",
              "isExpression": false,
              "asc": true,
              "nulls": "last"
            }
          ],
          "isUnique": false,
          "concurrently": false,
          "method": "btree",
          "with": {}
        }
      },
      "foreignKeys": {
        "roles_practice_id_practices_id_fk": {
          "name": "roles_practice_id_practices_id_fk",
          "tableFrom": "roles",
          "tableTo": "practices",
          "columnsFrom": [
            "practice_id"
          ],
          "columnsTo": [
            "id"
          ],
          "onDelete": "no action",
          "onUpdate": "no action"
        }
      },
      "compositePrimaryKeys": {},
      "uniqueConstraints": {},
      "policies": {},
      "checkConstraints": {},
      "isRLSEnabled": false
    },
    "public.user_course_assignments": {
      "name": "user_course_assignments",
      "schema": "",
      "columns": {
        "id": {
          "name": "id",
          "type": "serial",
          "primaryKey": true,
          "notNull": true
        },
        "user_id": {
          "name": "user_id",
          "type": "integer",
          "primaryKey": false,
          "notNull": true
        },
        "course_id": {
          "name": "course_id",
          "type": "integer",
          "primaryKey": false,
          "notNull": true
        },
        "assigned_at": {
          "name": "assigned_at",
          "type": "timestamp",
          "primaryKey": false,
          "notNull": true,
          "default": "now()"
        },
        "assigned_by_user_id": {
          "name": "assigned_by_user_id",
          "type": "integer",
          "primaryKey": false,
          "notNull": false
        }
      },
      "indexes": {
        "user_course_uniq": {
          "name": "user_course_uniq",
          "columns": [
            {
              "expression": "user_id",
              "isExpression": false,
              "asc": true,
              "nulls": "last"
            },
            {
              "expression": "course_id",
              "isExpression": false,
              "asc": true,
              "nulls": "last"
            }
          ],
          "isUnique": true,
          "concurrently": false,
          "method": "btree",
          "with": {}
        }
      },
      "foreignKeys": {
        "user_course_assignments_user_id_users_id_fk": {
          "name": "user_course_assignments_user_id_users_id_fk",
          "tableFrom": "user_course_assignments",
          "tableTo": "users",
          "columnsFrom": [
            "user_id"
          ],
          "columnsTo": [
            "id"
          ],
          "onDelete": "cascade",
          "onUpdate": "no action"
        },
        "user_course_assignments_course_id_courses_id_fk": {
          "name": "user_course_assignments_course_id_courses_id_fk",
          "tableFrom": "user_course_assignments",
          "tableTo": "courses",
          "columnsFrom": [
            "course_id"
          ],
          "columnsTo": [
            "id"
          ],
          "onDelete": "cascade",
          "onUpdate": "no action"
        },
        "user_course_assignments_assigned_by_user_id_users_id_fk": {
          "name": "user_course_assignments_assigned_by_user_id_users_id_fk",
          "tableFrom": "user_course_assignments",
          "tableTo": "users",
          "columnsFrom": [
            "assigned_by_user_id"
          ],
          "columnsTo": [
            "id"
          ],
          "onDelete": "no action",
          "onUpdate": "no action"
        }
      },
      "compositePrimaryKeys": {},
      "uniqueConstraints": {},
      "policies": {},
      "checkConstraints": {},
      "isRLSEnabled": false
    },
    "public.user_lesson_progress": {
      "name": "user_lesson_progress",
      "schema": "",
      "columns": {
        "id": {
          "name": "id",
          "type": "serial",
          "primaryKey": true,
          "notNull": true
        },
        "user_id": {
          "name": "user_id",
          "type": "integer",
          "primaryKey": false,
          "notNull": true
        },
        "lesson_id": {
          "name": "lesson_id",
          "type": "integer",
          "primaryKey": false,
          "notNull": true
        },
        "completed": {
          "name": "completed",
          "type": "boolean",
          "primaryKey": false,
          "notNull": false,
          "default": false
        },
        "completed_at": {
          "name": "completed_at",
          "type": "timestamp",
          "primaryKey": false,
          "notNull": false
        }
      },
      "indexes": {
        "user_lesson_uniq": {
          "name": "user_lesson_uniq",
          "columns": [
            {
              "expression": "user_id",
              "isExpression": false,
              "asc": true,
              "nulls": "last"
            },
            {
              "expression": "lesson_id",
              "isExpression": false,
              "asc": true,
              "nulls": "last"
            }
          ],
          "isUnique": true,
          "concurrently": false,
          "method": "btree",
          "with": {}
        }
      },
      "foreignKeys": {
        "user_lesson_progress_user_id_users_id_fk": {
          "name": "user_lesson_progress_user_id_users_id_fk",
          "tableFrom": "user_lesson_progress",
          "tableTo": "users",
          "columnsFrom": [
            "user_id"
          ],
          "columnsTo": [
            "id"
          ],
          "onDelete": "cascade",
          "onUpdate": "no action"
        },
        "user_lesson_progress_lesson_id_lessons_id_fk": {
          "name": "user_lesson_progress_lesson_id_lessons_id_fk",
          "tableFrom": "user_lesson_progress",
          "tableTo": "lessons",
          "columnsFrom": [
            "lesson_id"
          ],
          "columnsTo": [
            "id"
          ],
          "onDelete": "cascade",
          "onUpdate": "no action"
        }
      },
      "compositePrimaryKeys": {},
      "uniqueConstraints": {},
      "policies": {},
      "checkConstraints": {},
      "isRLSEnabled": false
    },
    "public.users": {
      "name": "users",
      "schema": "",
      "columns": {
        "id": {
          "name": "id",
          "type": "serial",
          "primaryKey": true,
          "notNull": true
        },
        "practice_id": {
          "name": "practice_id",
          "type": "integer",
          "primaryKey": false,
          "notNull": true
        },
        "name": {
          "name": "name",
          "type": "text",
          "primaryKey": false,
          "notNull": true
        },
        "email": {
          "name": "email",
          "type": "text",
          "primaryKey": false,
          "notNull": true
        },
        "role": {
          "name": "role",
          "type": "text",
          "primaryKey": false,
          "notNull": true,
          "default": "'front_desk'"
        },
        "status": {
          "name": "status",
          "type": "user_status",
          "typeSchema": "public",
          "primaryKey": false,
          "notNull": true,
          "default": "'invited'"
        },
        "avatar_initials": {
          "name": "avatar_initials",
          "type": "text",
          "primaryKey": false,
          "notNull": false
        },
        "created_at": {
          "name": "created_at",
          "type": "timestamp",
          "primaryKey": false,
          "notNull": true,
          "default": "now()"
        }
      },
      "indexes": {
        "users_email_practice_idx": {
          "name": "users_email_practice_idx",
          "columns": [
            {
              "expression": "email",
              "isExpression": false,
              "asc": true,
              "nulls": "last"
            },
            {
              "expression": "practice_id",
              "isExpression": false,
              "asc": true,
              "nulls": "last"
            }
          ],
          "isUnique": true,
          "concurrently": false,
          "method": "btree",
          "with": {}
        },
        "users_practice_idx": {
          "name": "users_practice_idx",
          "columns": [
            {
              "expression": "practice_id",
              "isExpression": false,
              "asc": true,
              "nulls": "last"
            }
          ],
          "isUnique": false,
          "concurrently": false,
          "method": "btree",
          "with": {}
        }
      },
      "foreignKeys": {
        "users_practice_id_practices_id_fk": {
          "name": "users_practice_id_practices_id_fk",
          "tableFrom": "users",
          "tableTo": "practices",
          "columnsFrom": [
            "practice_id"
          ],
          "columnsTo": [
            "id"
          ],
          "onDelete": "no action",
          "onUpdate": "no action"
        }
      },
      "compositePrimaryKeys": {},
      "uniqueConstraints": {},
      "policies": {},
      "checkConstraints": {},
      "isRLSEnabled": false
    }
  },
  "enums": {
    "public.content_scope": {
      "name": "content_scope",
      "schema": "public",
      "values": [
        "local",
        "global"
      ]
    },
    "public.course_level": {
      "name": "course_level",
      "schema": "public",
      "values": [
        "Beginner",
        "Intermediate",
        "Advanced"
      ]
    },
    "public.course_status": {
      "name": "course_status",
      "schema": "public",
      "values": [
        "draft",
        "published",
        "archived"
      ]
    },
    "public.doc_status": {
      "name": "doc_status",
      "schema": "public",
      "values": [
        "processing",
        "indexed",
        "failed"
      ]
    },
    "public.doc_type": {
      "name": "doc_type",
      "schema": "public",
      "values": [
        "pdf",
        "docx",
        "txt",
        "paste"
      ]
    },
    "public.lesson_type": {
      "name": "lesson_type",
      "schema": "public",
      "values": [
        "video",
        "reading",
        "quiz"
      ]
    },
    "public.user_status": {
      "name": "user_status",
      "schema": "public",
      "values": [
        "active",
        "invited",
        "inactive"
      ]
    }
  },
  "schemas": {},
  "sequences": {},
  "roles": {},
  "policies": {},
  "views": {},
  "_meta": {
    "columns": {},
    "schemas": {},
    "tables": {}
  }
}